llcuda/__init__.py
llcuda/__init___backup.py
llcuda/__init___pure.py
llcuda/chat.py
llcuda/embeddings.py
llcuda/jupyter.py
llcuda/models.py
llcuda/server.py
llcuda/utils.py
llcuda/_internal/__init__.py
llcuda/_internal/bootstrap.py
llcuda/_internal/registry.py
llcuda-1.1.1.post1.dist-info/licenses/LICENSE
llcuda-1.1.1.post1.dist-info/METADATA
llcuda-1.1.1.post1.dist-info/WHEEL
llcuda-1.1.1.post1.dist-info/top_level.txt
llcuda-1.1.1.post1.dist-info/RECORD
